{"default":{"identifier":"default","description":"Default capabilities for the Modbus Tool application","local":true,"windows":["main"],"permissions":["core:default","core:window:allow-close","core:window:allow-minimize","core:window:allow-maximize","core:window:allow-unmaximize","core:window:allow-show","core:window:allow-hide","core:window:allow-set-title","core:window:allow-set-size","core:window:allow-set-position","core:window:allow-center","core:window:allow-set-focus","core:window:allow-is-maximized","core:window:allow-is-minimized","core:window:allow-is-fullscreen","core:window:allow-set-fullscreen","core:window:allow-create","core:window:allow-destroy","core:event:default","core:event:allow-emit","core:event:allow-emit-to","core:event:allow-listen","shell:allow-open"]}}